LICENSE
MANIFEST.in
README.md
package.json
setup.py
vote_card/VoteCard.py
vote_card/__init__.py
vote_card/_imports_.py
vote_card/metadata.json
vote_card/package-info.json
vote_card/vote_card.min.js
vote_card/vote_card.min.js.map
vote_card.egg-info/PKG-INFO
vote_card.egg-info/SOURCES.txt
vote_card.egg-info/dependency_links.txt
vote_card.egg-info/top_level.txt