Metadata-Version: 1.1
Name: vote-card
Version: 0.0.1
Summary: Custom voting component
Home-page: UNKNOWN
Author: Yaakov Bressler <yb@yaakovbressler.com>
Author-email: UNKNOWN
License: MIT
Platform: UNKNOWN
Classifier: Framework :: Dash
